{
    "@class": "com.kony.gen.viz.model.component.KVizImage2",
    "DNDConfig": null,
    "_base64_": null,
    "_height_": {
        "type": "string",
        "value": "16dp"
    },
    "_left_": {
        "type": "string",
        "value": "0dp"
    },
    "_margin_": [
        0,
        0,
        0,
        0
    ],
    "_padding_": [
        0,
        0,
        0,
        0
    ],
    "_skin_": "s78a5f26c9f14cec9ebed1bb46098f80",
    "_src_": "bbcloseicon_1.png",
    "_top_": {
        "type": "string",
        "value": "0dp"
    },
    "_width_": {
        "type": "string",
        "value": "15dp"
    },
    "accessibilityconfig": {
        "a11yLabel": "Close",
        "a11yLabeli18n": "i18n.common.close",
        "a11yValue": ""
    },
    "canUpdateUI": true,
    "centerx": {
        "type": "string",
        "value": "50%"
    },
    "centery": {
        "type": "string",
        "value": "50%"
    },
    "containerweight": 100,
    "id": "imgCross",
    "imagescalemode": 1,
    "imagewhiledownloading": "img_transparent.png",
    "info": null,
    "invokedProperty": "src",
    "isvisible": false,
    "kuid": "f2b2bd72032548968c7c3b5eb289ee53",
    "name": "kony.ui.Image2",
    "parent": "flxCross",
    "pf": "frmMakeBillsPayment",
    "srcType": 1,
    "tooltip": "Close",
    "wType": "Image",
    "widgetalignment": 5,
    "zindex": 1
}