{
    "@class": "com.kony.gen.viz.model.component.KVizButton",
    "DNDConfig": null,
    "_height_": {
        "type": "string",
        "value": "40dp"
    },
    "_margin_": [
        6,
        6,
        6,
        6
    ],
    "_padding_": [
        0,
        0,
        0,
        0
    ],
    "_right_": {
        "type": "string",
        "value": "30.83%"
    },
    "_skin_": "sa611611b2f24e93bcfd09e1606c0d86",
    "_text_": "",
    "_width_": {
        "type": "string",
        "value": "12.50%"
    },
    "accessibilityconfig": {
        "a11yHint": "Click Cancel to cancel this transaction",
        "a11yLabel": "Cancel",
        "a11yLabeli18n": "i18n.TradeSupplyFinance.Cancel"
    },
    "canUpdateUI": true,
    "centery": {
        "type": "string",
        "value": "50%"
    },
    "containerweight": 100,
    "contentalignment": 5,
    "desktopweb": {
        "psp": {
            "hoverSkin": "s83729feaa224e359d660d5af05c4bac"
        }
    },
    "disabledSkins": {},
    "displaytext": true,
    "focusskin": "s434743e49c446699565893e4974ec52",
    "id": "btnCancel",
    "info": null,
    "isvisible": true,
    "kuid": "fe63955edbd24a4ea6b8cae6b9dc4e9d",
    "name": "kony.ui.Button",
    "parent": "TransferConfirmButtons",
    "pf": "userwidgetmodel",
    "texti18n": "i18n.transfers.Cancel",
    "tooltip": "",
    "wType": "Button",
    "zindex": 1
}