{
    "DNDConfig": null,
    "_height_": {
        "type": "string",
        "value": "150dp"
    },
    "_left_": {
        "type": "string",
        "value": ""
    },
    "_margin_": [
        0,
        0,
        0,
        0
    ],
    "_orientation_": 6,
    "_padding_": [
        0,
        0,
        0,
        0
    ],
    "_percent_": true,
    "_right_": {
        "type": "string",
        "value": ""
    },
    "_skin_": "s8a077aaedc841058caab8a6aaa04d14",
    "_top_": {
        "type": "string",
        "value": "20dp"
    },
    "_width_": {
        "type": "string",
        "value": "100%"
    },
    "allboxes": [],
    "autogrowmode": 0,
    "canUpdateUI": true,
    "centerx": {
        "type": "string",
        "value": ""
    },
    "children": [
        "CustomFooterMain"
    ],
    "clipbounds": true,
    "containerweight": 100,
    "enablescrolling": true,
    "id": "flxFooter",
    "info": null,
    "iscustomlayout": false,
    "isvisible": true,
    "kuid": "fdb8c2b445054c80826a70c4d467a6b6",
    "layouttype": 2,
    "name": "kony.ui.FlexContainer",
    "parent": "flxContent",
    "pf": "frmInternationalAddBeneficiaryConfirm",
    "responsiveData": {
        "b1": {},
        "b2": {},
        "b4": {}
    },
    "retaincontentalignment": false,
    "retainflexpositionproperties": false,
    "retainflowhorizontalalignment": false,
    "snapgridsize": 10,
    "snaptogrid": true,
    "wType": "FlexContainer",
    "widgetalignment": 1
}