{
    "DNDConfig": null,
    "_height_": {
        "type": "ref",
        "value": "preferred"
    },
    "_left_": {
        "type": "string",
        "value": "0dp"
    },
    "_margin_": [
        0,
        0,
        0,
        0
    ],
    "_orientation_": 6,
    "_padding_": [
        0,
        0,
        0,
        0
    ],
    "_percent_": true,
    "_skin_": "sfa77fa8edbe48c0b2a353776df1cb24",
    "_top_": {
        "type": "string",
        "value": "0dp"
    },
    "_width_": {
        "type": "string",
        "value": "100%"
    },
    "accessibilityconfig": {
        "a11yARIA": {
            "tabindex": -1
        }
    },
    "allboxes": [],
    "autogrowmode": 1,
    "canUpdateUI": true,
    "children": [
        "flxFields",
        "flxCancelAttachment",
        "flxPopup",
        "flxBankClearingLookup"
    ],
    "clipbounds": true,
    "containerweight": 100,
    "desktopweb": {
        "ide_onBreakpointChange": "AS_FlexContainer_d73114b1d07746b38eeee74968747820"
    },
    "enablescrolling": true,
    "id": "unifiedAddBeneficiary",
    "ide_onTouchEnd": "AS_FlexContainer_h23dda68e88743c589ada2a742aa4347",
    "ide_postShow": "AS_FlexContainer_e78ebb2f6d9d4f748c67588779fcde61",
    "ide_preShow": "AS_FlexContainer_g2321d20ed344bebb2b97241ef52d078",
    "iftextbox5": "",
    "iftextbox5label": "",
    "info": null,
    "iscustomlayout": false,
    "isvisible": true,
    "kuid": "b8816461498444aaa7083b874b4ed0af",
    "layouttype": 4,
    "name": "kony.ui.FlexContainer",
    "parent": "userwidgetmodel",
    "pf": "userwidgetmodel",
    "responsiveData": {
        "b1": {
            "ifTextBox5": "{\n  \"mapping\":\"{$.c.bankName}\",\n  \"placeHolder\":{\n    \"$.BREAKPTS.BP1\":\"{i.i18n.unifiedBeneficiary.enterBankName}\",\n    \"default\":\"{i.i18n.unifiedBeneficiary.enterBankName}\"\n  },\n  \"backendMapping\":\"bankName\"\n}\n",
            "ifTextBox5Label": "{\n\"text\" :\n{\n  \"$.BREAKPTS.BP1\":\"{i.i18n.payee.bankname}:\",\n  \"default\":\"{i.i18n.payee.bankname}:\"\n},\n\"helpTooltip\" : \"{i.i18n.transfers.bankName}\"\n}\n",
            "layoutType": 2
        },
        "b2": {
            "layoutType": 2
        },
        "b3": {
            "layoutType": 2
        },
        "b4": {
            "layoutType": 2
        }
    },
    "retaincontentalignment": false,
    "retainflexpositionproperties": false,
    "retainflowhorizontalalignment": false,
    "snapgridsize": 10,
    "snaptogrid": true,
    "wType": "FlexContainer",
    "widgetalignment": 1
}