{
    "@class": "com.kony.gen.viz.model.component.KVizLabel",
    "DNDConfig": null,
"__parentReadjusting__": false,
    "_height_": {
        "type": "ref",
        "value": "preferred"
    },
    "_left_": {
        "type": "number",
        "value": ""
    },
    "_margin_": [
        1,
        1,
        1,
        1
    ],
    "_padding_": [
        0,
        0,
        0,
        0
    ],
    "_skin_": "s948235facfb46438f08b864be0a55ef",
    "_text_": "",
    "_top_": {
        "type": "string",
        "value": "5dp"
    },
    "_width_": {
        "type": "ref",
        "value": "preferred"
    },
    "_wrapping_": 2,
    "accessibilityconfig": {
        "a11yARIA": {
            "tabindex": -1
        },
        "tagName": "span"
    },
    "android": {
        "textStyle": {
            "letterSpacing": 0,
            "strikeThrough": false
        }
    },
    "canUpdateUI": true,
    "centerx": {
        "type": "string",
        "value": "50%"
    },
    "centery": {
        "type": "number",
        "value": ""
    },
    "containerweight": 100,
    "contentalignment": 5,
    "id": "lblDBXAccount",
    "info": null,
    "ipad": {
        "psp": {
            "wrapping": 2
        }
    },
    "iphone": {
        "psp": {
            "wrapping": 2
        }
    },
    "isvisible": true,
    "kuid": "e10b0ae6ba3440e9ab0b1b14307751e5",
    "name": "kony.ui.Label",
    "parent": "flxDBXAccountInfo",
    "pf": "frmFastRecipientGateWay",
    "responsiveData": {
        "b3": {
            "centerX": {
                "type": "string",
                "value": ""
            },
            "centerY": {
                "type": "string",
                "value": ""
            },
            "left": {
                "type": "string",
                "value": "60dp"
            },
            "top": {
                "type": "string",
                "value": "15dp"
            }
        }
    },
    "texti18n": "i18n.FastTransfers.DBXAccount",
    "tooltip": "",
    "wType": "Label",
    "zindex": 1
}