{
    "@class": "com.kony.gen.viz.model.component.KVizLabel",
    "DNDConfig": null,
    "_height_": {
        "type": "ref",
        "value": "preferred"
    },
    "_i18n_text_": "i18n.billPay.addPayee",
    "_left_": {
        "type": "string",
        "value": "0"
    },
    "_margin_": [
        1,
        1,
        1,
        1
    ],
    "_padding_": [
        0,
        0,
        0,
        0
    ],
    "_skin_": "sa7698f19d1b473283864b966d8be272",
    "_text_": "",
    "_top_": {
        "type": "string",
        "value": "0"
    },
    "_width_": {
        "type": "ref",
        "value": "preferred"
    },
    "_wrapping_": 2,
    "accessibilityconfig": {
        "a11yARIA": {
            "tabindex": -1
        },
        "tagName": "h1"
    },
    "android": {
        "textStyle": {
            "letterSpacing": 0,
            "strikeThrough": false
        }
    },
    "canUpdateUI": true,
    "containerweight": 100,
    "contentalignment": 4,
    "id": "lblAddNewAccount",
    "info": null,
    "ipad": {
        "psp": {
            "wrapping": 2
        }
    },
    "iphone": {
        "psp": {
            "wrapping": 2
        }
    },
    "iscustomlayout": false,
    "isvisible": true,
    "kuid": "c95ac53f39d740b99a24f9a786836367",
    "name": "kony.ui.Label",
    "parent": "flxMain",
    "pf": "frmInternationalAddBeneficiary",
    "responsiveData": {
        "b1": {
            "i18n_text": "i18n.billPay.addPayee",
            "left": {
                "type": "string",
                "value": "85dp"
            },
            "top": {
                "type": "string",
                "value": "25dp"
            }
        },
        "b2": {
            "left": {
                "type": "string",
                "value": "3%"
            },
            "top": {
                "type": "string",
                "value": "25dp"
            }
        },
        "b3": {
            "isVisible": false
        },
        "b4": {
            "left": {
                "type": "string",
                "value": "85dp"
            },
            "top": {
                "type": "string",
                "value": "25dp"
            }
        }
    },
    "retaincontentalignment": false,
    "retainflexpositionproperties": false,
    "texti18n": "i18n.billPay.addPayee",
    "tooltip": "",
    "wType": "Label"
}