{
    "AS_FlexContainer_cb3dd3c0e72b442581bc42cfd00b7f6d": {
        "id": "AS_FlexContainer_cb3dd3c0e72b442581bc42cfd00b7f6d",
        "type": "ACTION_SEQUENCE",
        "params": [{
            "datatype": "collection",
            "name": "eventobject"
        }],
        "contextObj": {
            "name": "userwidgetmodel",
            "type": "userwidgets",
            "KUID": "u022510e97484905b42c9f7a748ec7c5"
        },
        "language": "js",
        "actions": [{
            "id": "INVOKE_FUNCTION__f3c1319ea563436890bc4f4558272a39",
            "type": "INVOKE_FUNCTION",
            "sequenceKUID": "postShow",
            "display": "postShow",
            "inputparams": [],
            "parentId": null,
            "callbackType": null,
            "disabled": null,
            "source": "controller"
        }]
    }
}