{
    "AS_FlexContainer_fa4d33ef5c764cbf85a562b60e5b4e01": {
        "id": "AS_FlexContainer_fa4d33ef5c764cbf85a562b60e5b4e01",
        "type": "ACTION_SEQUENCE",
        "params": [{
            "datatype": "collection",
            "name": "eventobject"
        }],
        "contextObj": {
            "KUID": "u8f0ba6556d7488ab3da70e8d3fe53a9",
            "name": "userwidgetmodel",
            "type": "userwidgets"
        },
        "language": "js",
        "actions": [{
            "id": "ADD_SNIPPET_d9661a39bd3c4b62860be5938e9571d1",
            "type": "ADD_SNIPPET",
            "codeSnippet": "var currentPage = 0;\nvar totalPages = 0;\nvar currentPageSize = 0;\nvar totalRecordsCount = 0;\nvar startIndex = 1;\nvar endIndex = 0;\nvar isMaxLimitReached = false;\nvar tokens = {\n  \"currentPage\" :\"\",\n  \"totalPages\":\"\",\n  \"currentPageSize\":\"\",\n  \"totalRecords\":\"\",\n  \"startIndex\":\"\",\n  \"endIndex\":\"\"\n};",
            "parentId": null
        }]
    }
}