{
    "@class": "com.kony.gen.viz.model.component.KVizUserWidget",
    "DNDConfig": null,
    "_bottom_": {
        "type": "number",
        "value": ""
    },
    "_children_": [],
    "_height_": {
        "type": "ref",
        "value": "preferred"
    },
    "_left_": {
        "type": "string",
        "value": ""
    },
    "_margin_": [
        0,
        0,
        0,
        0
    ],
    "_orientation_": 1,
    "_padding_": [
        0,
        0,
        0,
        0
    ],
    "_percent_": true,
    "_skin_": "s24c92fc23b14f5484b693ee9b8a9b35",
    "_top_": {
        "type": "string",
        "value": "0dp"
    },
    "_width_": {
        "type": "string",
        "value": "100%"
    },
    "android": {},
    "androidwearos": {},
    "areflexpropsreferenced": false,
    "autogrowmode": 1,
    "canUpdateUI": true,
    "centerx": {
        "type": "string",
        "value": "50%"
    },
    "clipbounds": true,
    "containerweight": 0,
    "dataDiffs": {
        "btnAction4": {
            "__events__": {},
            "__info__": {
                "kuid": "ib8c8be8e053426b9fa73ab056571cba",
                "srcKUID": "g6cf78fcd4414c8990084e1ecfc99028",
                "wType": "Button"
            },
            "responsiveData": {}
        },
        "btnAction5": {
            "__events__": {},
            "__info__": {
                "kuid": "b34041dc686c406f9aa1bfcc24640720",
                "srcKUID": "aa8a3fedf91b4d6487cc28e1d4e2f4d4",
                "wType": "Button"
            },
            "responsiveData": {
                "b1": {},
                "b2": {},
                "b3": {},
                "b4": {}
            }
        },
        "btnAction6": {
            "__events__": {},
            "__info__": {
                "kuid": "a7b95e62bbcd4f6f82a526059e83ab4c",
                "srcKUID": "a59805c649204873b36701629f8eb0b8",
                "wType": "Button"
            },
            "responsiveData": {
                "b1": {},
                "b2": {},
                "b3": {},
                "b4": {}
            }
        },
        "contractList": {
            "__events__": {},
            "__info__": {
                "isRoot": true,
                "kuid": "fc23097b53ec4df2946499d350a822b7",
                "srcKUID": "h032c7bf11064068956e72e559572e85",
                "wType": "FlexContainer"
            },
            "isVisible": false,
            "responsiveData": {
                "b1": {
                    "isVisible": false
                }
            }
        },
        "flxClear": {
            "__events__": {},
            "__info__": {
                "kuid": "iaac0be52df84baea21426dca28a930b",
                "srcKUID": "f5301e58797b4d3e8c8fe68449ac5b93",
                "wType": "FlexContainer"
            }
        },
        "flxCol1": {
            "__events__": {},
            "__info__": {
                "kuid": "ce44665c666146cf912b551c419c6030",
                "srcKUID": "b0d105675da2423c8f1f970b57d161c0",
                "wType": "FlexContainer"
            }
        },
        "flxCol2": {
            "__events__": {},
            "__info__": {
                "kuid": "afda72701c444e4a9c5df205ee6e6fe0",
                "srcKUID": "af1cc904c2524657891b9b4aff4d72f7",
                "wType": "FlexContainer"
            }
        },
        "flxCol3": {
            "__events__": {},
            "__info__": {
                "kuid": "gb56948873af471d8d23a344bee76dc1",
                "srcKUID": "b0706d5e7a454f23806001e38a118043",
                "wType": "FlexContainer"
            }
        },
        "flxCol4": {
            "__events__": {},
            "__info__": {
                "kuid": "ffdf3934f83d474c859201c610b1fa7b",
                "srcKUID": "d30a33e00daf4923b81ce74ff43530ad",
                "wType": "FlexContainer"
            }
        },
        "flxConfirmButtons": {
            "__events__": {},
            "__info__": {
                "kuid": "i83c419bc6e6451dad52ce2e76ba8bf1",
                "srcKUID": "df49009594b54b6ba0cbbba68ee6a26f",
                "wType": "FlexContainer"
            }
        },
        "flxContent": {
            "__events__": {},
            "__info__": {
                "kuid": "ac89660658c449a5969b4f098a82026e",
                "srcKUID": "ea83c52e47c948b38c1ff3567343e929",
                "wType": "FlexContainer"
            }
        },
        "flxContract": {
            "__events__": {},
            "__info__": {
                "kuid": "cefe9cc5caee4b80b059f5a598d6c1d0",
                "srcKUID": "a1c9b654306848568f5605e2e76adc5a",
                "wType": "FlexContainer"
            }
        },
        "flxContractsHeader": {
            "__events__": {},
            "__info__": {
                "kuid": "c264bbfca1ae4a24b1f1911b2ff9577d",
                "srcKUID": "b0dfc4b03c7a4dd295dc0adb9670540f",
                "wType": "FlexContainer"
            }
        },
        "flxNoResultsFound": {
            "__events__": {},
            "__info__": {
                "kuid": "a786d144d4cf4b42bd6f289bb44e2618",
                "srcKUID": "j5295249526d4d9483aa0c4d1555e8a5",
                "wType": "FlexContainer"
            }
        },
        "flxRow": {
            "__events__": {},
            "__info__": {
                "kuid": "ed76839b261e49daa06a2b29afc857e6",
                "srcKUID": "bfe6c4f76107425eb664fc404d2655f1",
                "wType": "FlexContainer"
            }
        },
        "flxSearch": {
            "__events__": {},
            "__info__": {
                "kuid": "h7b07af055fc46bd85f06f22d3c36ebf",
                "srcKUID": "cac543c339184fc9b0ded16a933bf1ff",
                "wType": "FlexContainer"
            }
        },
        "flxSearchBtn": {
            "__events__": {},
            "__info__": {
                "kuid": "ac38855233244a75be15332b3c42a808",
                "srcKUID": "b83320258b8a4a28a4e29137e4ca470f",
                "wType": "FlexContainer"
            }
        },
        "flxSeperatorBottom": {
            "__events__": {},
            "__info__": {
                "kuid": "dc4bfbca3bdc440f8bab35ec2e85757f",
                "srcKUID": "f1bd6399747e406589fd6c4dc4a8e9a2",
                "wType": "FlexContainer"
            }
        },
        "flxSeperatorHeader": {
            "__events__": {},
            "__info__": {
                "kuid": "fa266ec23dfe42b8b1799d15245587a7",
                "srcKUID": "g3d2e02f0da745ceacb1cc3d72eea8fc",
                "wType": "FlexContainer"
            }
        },
        "imgCol1": {
            "__events__": {},
            "__info__": {
                "kuid": "bdf27be904fd44c6b6c56682e4abd69d",
                "srcKUID": "d0c2b9db632345b48a66ffd71f71433f",
                "wType": "Image"
            },
            "src": "sorting_next.png"
        },
        "imgCol2": {
            "__events__": {},
            "__info__": {
                "kuid": "de1367857a22425fa4f1b1e5f885bd6b",
                "srcKUID": "b9f56d71b94546b689ab4f03956afe47",
                "wType": "Image"
            },
            "src": "sorting.png"
        },
        "imgCross": {
            "__events__": {},
            "__info__": {
                "kuid": "af54befcae694147bc15c3098e905174",
                "srcKUID": "c06592ea8b8944049616b8fad67e3a32",
                "wType": "Image"
            }
        },
        "imgSelectAll": {
            "__events__": {},
            "__info__": {
                "kuid": "a80d15a35a1c4c429955e5a28166af3c",
                "srcKUID": "af5d8bccd8874f149e5261ae093f3c63",
                "wType": "Image"
            }
        },
        "lblCheckBoxSelectAll": {
            "__events__": {},
            "__info__": {
                "kuid": "b2ea1920a1ae4aee82b7b5b5c5de6180",
                "srcKUID": "b120d9eb66dd40969c57c9480b13f59f",
                "wType": "Label"
            }
        },
        "lblCol1": {
            "__events__": {},
            "__info__": {
                "kuid": "ce83d95af60b4491a226278d758d4fae",
                "srcKUID": "a189a6d78ad8457b87dcc02ba7da7379",
                "wType": "Label"
            },
            "i18n_text": "i18n.approvals.contract",
            "responsiveData": {
                "b4": {}
            },
            "text": ""
        },
        "lblCol2": {
            "__events__": {},
            "__info__": {
                "kuid": "a48fd5bc1ed14b758379b2f21f0c1e0e",
                "srcKUID": "b80197c34c4a4ee582aab41568beab58",
                "wType": "Label"
            },
            "i18n_text": "i18n.payments.identityNumber",
            "responsiveData": {},
            "text": ""
        },
        "lblCol4": {
            "__events__": {},
            "__info__": {
                "kuid": "d4587d400b8143b38928065a73177e69",
                "srcKUID": "f0884b77f5304effa77ff6a8a809872f",
                "wType": "Label"
            }
        },
        "lblColumn3": {
            "__events__": {},
            "__info__": {
                "kuid": "d980f3d89b6346959595d577915779a2",
                "srcKUID": "a1580167dcd643ed9e173595260e2299",
                "wType": "Label"
            },
            "i18n_text": "i18n.unifiedBeneficiary.SelectedCIF",
            "responsiveData": {},
            "text": ""
        },
        "lblDescription": {
            "__events__": {},
            "__info__": {
                "kuid": "c7d4e92a33c84ce9a3e22368ee34ece9",
                "srcKUID": "f9f10517b6be45f89e7a05faf941f302",
                "wType": "Label"
            }
        },
        "lblHeader": {
            "__events__": {},
            "__info__": {
                "kuid": "ab1820cfc999442ab0e0ea577061e4ba",
                "srcKUID": "g44ebf8aa6764d42a01d06e0b9ca2361",
                "wType": "Label"
            }
        },
        "lblNoResultsFound": {
            "__events__": {},
            "__info__": {
                "kuid": "h8fb666bd8864c9a92f5bd07162a684d",
                "srcKUID": "bc435e09cc4e410b873e74d405ed67f6",
                "wType": "Label"
            }
        },
        "lblSearch": {
            "__events__": {},
            "__info__": {
                "kuid": "e58b0d2811cc400bb31023ae84a18cec",
                "srcKUID": "e189ea51203249b2bdec95388a4242c3",
                "wType": "Label"
            }
        },
        "lblSeparator": {
            "__events__": {},
            "__info__": {
                "kuid": "ae84e0739e77458494f24b9ebcdad8d0",
                "srcKUID": "j962c76be4d74abd8e25577ce6775360",
                "wType": "Label"
            }
        },
        "segContract": {
            "__events__": {},
            "__info__": {
                "kuid": "c9c89198ffd3434f88ff99567d678fe1",
                "srcKUID": "c61794ee05484b15b978d264959eb6b5",
                "wType": "Segment"
            }
        },
        "txtSearch": {
            "__events__": {},
            "__info__": {
                "kuid": "dce23ea7da0f437eaf379f635511ffee",
                "srcKUID": "b93a25583a1a402fb3e24ff7bc47990b",
                "wType": "TextField"
            }
        }
    },
    "desktopweb": {},
    "enablescrolling": true,
    "id": "contractList",
    "info": null,
    "ipad": {},
    "iphone": {},
    "iscustomlayout": false,
    "isdatareferenced": false,
    "isvisible": false,
    "kuid": "fc23097b53ec4df2946499d350a822b7",
    "layouttype": 2,
    "masterType": 0,
    "name": "kony.ui.UserWidgetInstance",
    "parent": "flxContractList",
    "pf": "frmAddBeneficiaryEuro",
    "responsiveData": {
        "b1": {}
    },
    "retaincontentalignment": false,
    "retainflexpositionproperties": false,
    "retainflowhorizontalalignment": false,
    "snapgridsize": 10,
    "snaptogrid": true,
    "sourceUserWidget": "h032c7bf11064068956e72e559572e85",
    "spabb": {},
    "tabrcandroid": {},
    "vizProps": {
        "hidewidgethierarchy": false
    },
    "wType": "UserWidgetInstance",
    "zindex": 1
}