{
    "@class": "com.kony.gen.viz.model.component.KVizButton",
    "DNDConfig": null,
    "_bottom_": {
        "type": "number",
        "value": ""
    },
    "_height_": {
        "type": "string",
        "value": "40dp"
    },
    "_left_": {
        "type": "string",
        "value": "60.00103244326005%"
    },
    "_margin_": [
        6,
        6,
        6,
        6
    ],
    "_padding_": [
        0,
        0,
        0,
        0
    ],
    "_right_": {
        "type": "string",
        "value": "3.77%"
    },
    "_skin_": "s95376e131db404ebbe858e3b39046ef",
    "_text_": "",
    "_top_": {
        "type": "number",
        "value": ""
    },
    "_width_": {
        "type": "string",
        "value": "40%"
    },
    "accessibilityconfig": {},
    "canUpdateUI": true,
    "centerx": {
        "type": "string",
        "value": ""
    },
    "centery": {
        "type": "string",
        "value": "50%"
    },
    "containerweight": 100,
    "contentalignment": 5,
    "desktopweb": {
        "psp": {
            "hoverSkin": "s7ab6326aaf94c28b90b61fcb1b54547"
        }
    },
    "displaytext": true,
    "focusskin": "sfd0ce0d7f454c9f83c7e815a90a8a55",
    "id": "btnConfirm",
    "info": null,
    "isvisible": true,
    "kuid": "i6d186c8ad4e4c8484c14ebebec23568",
    "name": "kony.ui.Button",
    "parent": "flxButtonsContainer",
    "pf": "frmMakeTelebirrPayment",
    "responsiveData": {
        "b1": {
            "right": {
                "type": "string",
                "value": "3%"
            }
        },
        "b3": {
            "centerY": {
                "type": "string",
                "value": ""
            },
            "right": {
                "type": "string",
                "value": "2%"
            },
            "top": {
                "type": "string",
                "value": "20dp"
            }
        },
        "b4": {
            "right": {
                "type": "string",
                "value": "3%"
            }
        },
        "b5": {
            "right": {
                "type": "string",
                "value": "3%"
            }
        }
    },
    "texti18n": "i18n.common.proceed",
    "tooltip": "",
    "wType": "Button",
    "zindex": 1
}