{
    "AS_Image_f99ce236887e40038b8466bf4034c1e4": {
        "id": "AS_Image_f99ce236887e40038b8466bf4034c1e4",
        "type": "ACTION_SEQUENCE",
        "params": [{
            "datatype": "collection",
            "name": "eventobject"
        }, {
            "datatype": "string",
            "name": "x"
        }, {
            "datatype": "string",
            "name": "y"
        }],
        "contextObj": {
            "name": "frmSelectTransferTypeNew",
            "type": "forms",
            "platform": "",
            "KUID": "g2358821428d4bde8a5747fc98a2a89e"
        },
        "language": "js",
        "actions": [{
            "id": "INVOKE_FUNCTION__f9bb681363f34a8ea3c4c93aab51db82",
            "type": "INVOKE_FUNCTION",
            "sequenceKUID": "iPhoneBackNavigation",
            "display": "iPhoneBackNavigation",
            "inputparams": [],
            "parentId": null,
            "callbackType": null,
            "disabled": null,
            "source": "controller"
        }]
    }
}