{
    "DNDConfig": null,
    "_height_": {
        "type": "string",
        "value": "1dp"
    },
    "_left_": {
        "type": "string",
        "value": "10dp"
    },
    "_margin_": [
        0,
        0,
        0,
        0
    ],
    "_orientation_": 6,
    "_padding_": [
        0,
        0,
        0,
        0
    ],
    "_percent_": true,
    "_skin_": "sd3a991a352b4393a7ba7f7ee976b318",
    "_top_": {
        "type": "string",
        "value": "10dp"
    },
    "_width_": {
        "type": "string",
        "value": "100%"
    },
    "accessibilityconfig": {
        "a11yHidden": true
    },
    "allboxes": [],
    "canUpdateUI": true,
    "centery": {
        "type": "number",
        "value": ""
    },
    "children": [],
    "clipbounds": true,
    "containerweight": 100,
    "enablescrolling": true,
    "id": "flxDot11",
    "info": null,
    "iscustomlayout": false,
    "isvisible": true,
    "kuid": "i73a8d3a213a4bb7b0726d01f827c475",
    "layouttype": 2,
    "name": "kony.ui.FlexContainer",
    "parent": "flxField11",
    "pf": "userwidgetmodel",
    "responsiveData": {
        "b1": {
            "centerY": {
                "type": "string",
                "value": "10dp"
            },
            "height": {
                "type": "string",
                "value": "10dp"
            },
            "left": {
                "type": "string",
                "value": "5dp"
            },
            "skin": "sbffe54c0cb94c738eb94257cee4balp",
            "top": {
                "type": "string",
                "value": "5dp"
            },
            "width": {
                "type": "string",
                "value": "10dp"
            }
        },
        "b2": {
            "centerY": {
                "type": "string",
                "value": "10dp"
            },
            "height": {
                "type": "string",
                "value": "10dp"
            },
            "left": {
                "type": "string",
                "value": "0dp"
            },
            "skin": "sbffe54c0cb94c738eb94257cee4balp",
            "top": {
                "type": "string",
                "value": "7dp"
            },
            "width": {
                "type": "string",
                "value": "10dp"
            }
        },
        "b3": {
            "centerY": {
                "type": "string",
                "value": "10dp"
            },
            "height": {
                "type": "string",
                "value": "10dp"
            },
            "left": {
                "type": "string",
                "value": "0dp"
            },
            "skin": "sbffe54c0cb94c738eb94257cee4balp",
            "top": {
                "type": "string",
                "value": "0dp"
            },
            "width": {
                "type": "string",
                "value": "10dp"
            }
        },
        "b4": {
            "centerY": {
                "type": "string",
                "value": "10dp"
            },
            "height": {
                "type": "string",
                "value": "10dp"
            },
            "left": {
                "type": "string",
                "value": "5dp"
            },
            "skin": "sbffe54c0cb94c738eb94257cee4balp",
            "top": {
                "type": "string",
                "value": "5dp"
            },
            "width": {
                "type": "string",
                "value": "10dp"
            }
        }
    },
    "retaincontentalignment": false,
    "retainflexpositionproperties": false,
    "retainflowhorizontalalignment": false,
    "snapgridsize": 10,
    "snaptogrid": true,
    "wType": "FlexContainer",
    "widgetalignment": 1,
    "zindex": 1
}