{
    "@class": "com.kony.gen.viz.model.component.KVizLabel",
    "DNDConfig": null,
    "_height_": {
        "type": "ref",
        "value": "preferred"
    },
    "_left_": {
        "type": "string",
        "value": "20dp"
    },
    "_margin_": [
        1,
        1,
        1,
        1
    ],
    "_padding_": [
        0,
        0,
        5,
        0
    ],
    "_skin_": "s41d06c736c84b6595f23a7437081016",
    "_text_": "",
    "_top_": {
        "type": "string",
        "value": "0dp"
    },
    "_width_": {
        "type": "ref",
        "value": "preferred"
    },
    "_wrapping_": 2,
    "accessibilityconfig": {
        "a11yARIA": {
            "tabindex": -1
        },
        "tagName": "span"
    },
    "android": {
        "textStyle": {
            "letterSpacing": 0,
            "strikeThrough": false
        }
    },
    "canUpdateUI": true,
    "centery": {
        "type": "string",
        "value": "50%"
    },
    "containerweight": 100,
    "contentalignment": 4,
    "id": "lblPayeeVerificationTitle",
    "info": null,
    "ipad": {
        "psp": {
            "wrapping": 2
        }
    },
    "iphone": {
        "psp": {
            "wrapping": 2
        }
    },
    "isvisible": true,
    "kuid": "e793e9246d294bf788bb0d976fe4c27a",
    "name": "kony.ui.Label",
    "paddinginpixel": false,
    "parent": "flxBenVerificationDetails",
    "pf": "frmBeneficiaryDetailsEurope",
    "texti18n": "i18n.UnifiedAddBeneficiary.ManageVerifylabel",
    "tooltip": "",
    "wType": "Label",
    "zindex": 1
}