{
    "@class": "com.kony.gen.viz.model.component.KVizLabel",
    "DNDConfig": null,
    "_bottom_": {
        "type": "string",
        "value": "0dp"
    },
    "_height_": {
        "type": "ref",
        "value": "preferred"
    },
    "_left_": {
        "type": "string",
        "value": "11.07%"
    },
    "_margin_": [
        1,
        1,
        1,
        1
    ],
    "_padding_": [
        0,
        0,
        2,
        0
    ],
    "_skin_": "s696f30688214a879f3066e26bd00d77",
    "_text_": "",
    "_top_": {
        "type": "string",
        "value": "25dp"
    },
    "_width_": {
        "type": "ref",
        "value": "preferred"
    },
    "_wrapping_": 2,
    "accessibilityconfig": {
        "a11yARIA": {
            "tabindex": -1
        },
        "a11yLabel": "Domestic transfer",
        "a11yLabeli18n": "i18n.payments.domesticTransfer",
        "tagName": "h1"
    },
    "android": {
        "textStyle": {
            "letterSpacing": 0,
            "strikeThrough": false
        }
    },
    "canUpdateUI": true,
    "centerx": {
        "type": "string",
        "value": ""
    },
    "centery": {
        "type": "number",
        "value": ""
    },
    "containerweight": 100,
    "contentalignment": 1,
    "id": "lblTransfersHeading",
    "info": null,
    "ipad": {
        "psp": {
            "wrapping": 2
        }
    },
    "iphone": {
        "psp": {
            "wrapping": 2
        }
    },
    "isvisible": true,
    "kuid": "d344315e8c764aaba821727ce36f5db5",
    "name": "kony.ui.Label",
    "paddinginpixel": false,
    "parent": "flxSectionHeader",
    "pf": "frmUTFDomesticTransfer",
    "responsiveData": {
        "b1": {},
        "b2": {
            "bottom": {
                "type": "number",
                "value": "0"
            },
            "centerY": {
                "type": "string",
                "value": ""
            }
        },
        "b3": {
            "height": {
                "type": "string",
                "value": "0dp"
            },
            "isVisible": false
        },
        "b4": {}
    },
    "texti18n": "i18n.hamburger.transfers",
    "tooltip": "",
    "wType": "Label",
    "zindex": 1
}