{
    "@class": "com.kony.gen.viz.model.component.KVizLabel",
    "DNDConfig": null,
    "_height_": {
        "type": "ref",
        "value": "preferred"
    },
    "_left_": {
        "type": "string",
        "value": "0"
    },
    "_margin_": [
        1,
        1,
        1,
        1
    ],
    "_padding_": [
        0,
        0,
        0,
        0
    ],
    "_skin_": "s4d19503e6cb4941a30bda3dcff671b5",
    "_text_": "s",
    "_top_": {
        "type": "string",
        "value": "0"
    },
    "_width_": {
        "type": "ref",
        "value": "preferred"
    },
    "_wrapping_": 2,
    "android": {
        "textStyle": {
            "letterSpacing": 0,
            "strikeThrough": false
        }
    },
    "canUpdateUI": true,
    "centerx": {
        "type": "string",
        "value": "50%"
    },
    "centery": {
        "type": "string",
        "value": "50%"
    },
    "containerweight": 100,
    "contentalignment": 5,
    "id": "lblDefaultAccountUser",
    "info": null,
    "ipad": {
        "psp": {
            "wrapping": 2
        }
    },
    "iphone": {
        "psp": {
            "wrapping": 2
        }
    },
    "iscustomlayout": false,
    "isvisible": true,
    "kuid": "a4df249454cb433b824f226a92c35ff4",
    "name": "kony.ui.Label",
    "parent": "flxDefaultAccountUser",
    "pf": "frmP2PSettings",
    "responsiveData": {
        "b1": {},
        "b2": {},
        "b3": {},
        "b4": {}
    },
    "retaincontentalignment": false,
    "retainflexpositionproperties": false,
    "tooltip": "",
    "wType": "Label"
}